pacbio_data_processing/__init__.py
pacbio_data_processing/bam.py
pacbio_data_processing/bam_file_filter.py
pacbio_data_processing/bam_utils.py
pacbio_data_processing/cigar.py
pacbio_data_processing/constants.py
pacbio_data_processing/errors.py
pacbio_data_processing/external.py
pacbio_data_processing/filters.py
pacbio_data_processing/ipd.py
pacbio_data_processing/logs.py
pacbio_data_processing/methylation.py
pacbio_data_processing/parameters.py
pacbio_data_processing/plots.py
pacbio_data_processing/sam.py
pacbio_data_processing/sentinel.py
pacbio_data_processing/sm_analysis.py
pacbio_data_processing/sm_analysis_gui.py
pacbio_data_processing/summary.py
pacbio_data_processing/templates.py
pacbio_data_processing/types.py
pacbio_data_processing/utils.py
pacbio_data_processing/ui/__init__.py
pacbio_data_processing/ui/cl.py
pacbio_data_processing/ui/common.py
pacbio_data_processing/ui/gui.py
pacbio_data_processing/ui/options.py
pacbiodataprocessing-1.3.0.dist-info/entry_points.txt
pacbiodataprocessing-1.3.0.dist-info/COPYING
pacbiodataprocessing-1.3.0.dist-info/WHEEL
pacbiodataprocessing-1.3.0.dist-info/METADATA
pacbiodataprocessing-1.3.0.dist-info/RECORD
