Metadata-Version: 2.1
Name: PacbioDataProcessing
Version: 1.3.0
Summary: Tools to process PacBio sequencing data at molecule level
Keywords: PacBio,DNA,biology,sequencing,methylations
Author-email: David Palao <david.palao@gmail.com>, David Velázquez <david.velazquez@protonmail.com>
Maintainer-email: David Palao <david.palao@gmail.com>
Requires-Python: >=3.8
Classifier: Development Status :: 5 - Production/Stable
Classifier: Environment :: Console
Classifier: Intended Audience :: Science/Research
Classifier: License :: OSI Approved :: GNU General Public License v3 or later (GPLv3+)
Classifier: Natural Language :: English
Classifier: Programming Language :: Python :: 3
Classifier: Programming Language :: Python :: 3.9
Classifier: Operating System :: OS Independent
Classifier: Topic :: Scientific/Engineering :: Bio-Informatics
Requires-Dist: biopython
Requires-Dist: pysam
Requires-Dist: pyfaidx
Requires-Dist: matplotlib
Requires-Dist: seaborn~=0.12
Requires-Dist: pandas
Requires-Dist: numpy
Requires-Dist: bump2version ; extra == "dev"
Requires-Dist: flit ; extra == "dev"
Requires-Dist: watchdog ; extra == "dev"
Requires-Dist: Sphinx ; extra == "doc"
Requires-Dist: Sphinx-Substitution-Extensions ; extra == "doc"
Requires-Dist: sphinx-prompt ; extra == "doc"
Requires-Dist: Gooey ; extra == "gui"
Requires-Dist: psutil ; extra == "test"
Requires-Dist: pytest ; extra == "test"
Requires-Dist: pytest-runner ; extra == "test"
Requires-Dist: pytest-cov ; extra == "test"
Requires-Dist: pytest-subtests ; extra == "test"
Requires-Dist: flake8 ; extra == "test"
Requires-Dist: tox ; extra == "test"
Requires-Dist: coverage ; extra == "test"
Project-URL: Documentation, https://pacbio-data-processing.readthedocs.io/en/latest/
Project-URL: Source, https://gitlab.com/dvelazquez/pacbio-data-processing
Provides-Extra: dev
Provides-Extra: doc
Provides-Extra: gui
Provides-Extra: test
